Metadata-Version: 1.1
Name: russiannames
Version: 1.0
Summary: Russian names parser, gender identification and processing tools
Home-page: https://github.com/datacoon/russiannames
Author: Ivan Begtin
Author-email: ivan@begtin.tech
License: BSD
Keywords: russian names surnames gender
Platform: UNKNOWN
Classifier: Development Status :: 2 - Pre-Alpha
Classifier: Intended Audience :: Developers
Classifier: License :: OSI Approved :: BSD License
Classifier: Natural Language :: English
Classifier: Programming Language :: Python :: 3
Classifier: Programming Language :: Python :: 3.3
Classifier: Programming Language :: Python :: 3.4
Classifier: Programming Language :: Python :: 3.5
Classifier: Programming Language :: Python :: 3.6
Classifier: Programming Language :: Python :: Implementation :: CPython
Classifier: Programming Language :: Python :: Implementation :: PyPy
